odoo/addons/shopinvader_validation_token/README.rst
odoo/addons/shopinvader_validation_token/__init__.py
odoo/addons/shopinvader_validation_token/__manifest__.py
odoo/addons/shopinvader_validation_token/data/ir_cron.xml
odoo/addons/shopinvader_validation_token/data/mail_template.xml
odoo/addons/shopinvader_validation_token/i18n/shopinvader_validation_token.pot
odoo/addons/shopinvader_validation_token/models/__init__.py
odoo/addons/shopinvader_validation_token/models/shopinvader_backend.py
odoo/addons/shopinvader_validation_token/models/shopinvader_notification.py
odoo/addons/shopinvader_validation_token/models/shopinvader_security_token.py
odoo/addons/shopinvader_validation_token/readme/CONFIGURE.rst
odoo/addons/shopinvader_validation_token/readme/CONTRIBUTORS.rst
odoo/addons/shopinvader_validation_token/readme/DESCRIPTION.rst
odoo/addons/shopinvader_validation_token/security/shopinvader_security_token.xml
odoo/addons/shopinvader_validation_token/services/__init__.py
odoo/addons/shopinvader_validation_token/services/customer_service.py
odoo/addons/shopinvader_validation_token/static/description/index.html
odoo/addons/shopinvader_validation_token/tests/__init__.py
odoo/addons/shopinvader_validation_token/tests/common.py
odoo/addons/shopinvader_validation_token/tests/test_customer_service.py
odoo/addons/shopinvader_validation_token/views/shopinvader_backend.xml
odoo/addons/shopinvader_validation_token/views/shopinvader_security_token.xml
odoo14_addon_shopinvader_validation_token-14.0.1.0.2.dist-info/METADATA
odoo14_addon_shopinvader_validation_token-14.0.1.0.2.dist-info/WHEEL
odoo14_addon_shopinvader_validation_token-14.0.1.0.2.dist-info/top_level.txt
odoo14_addon_shopinvader_validation_token-14.0.1.0.2.dist-info/RECORD
