Metadata-Version: 2.1
Name: odoo14-addon-shopinvader-validation-token
Version: 14.0.1.0.2
Summary: Implements a security layer on the registration and/or customer mode. To ensure a customer doesn't use the email of somebody else, it generates a token/code send using notification and the customer has to fill it on the front-side.
Home-page: https://github.com/shopinvader/odoo-shopinvader
Author: ACSONE SA/NV
License: AGPL-3
Platform: UNKNOWN
Classifier: Programming Language :: Python
Classifier: Framework :: Odoo
Classifier: Framework :: Odoo :: 14.0
Classifier: License :: OSI Approved :: GNU Affero General Public License v3
Requires-Python: >=3.6
Requires-Dist: odoo14-addon-shopinvader
Requires-Dist: odoo (<14.1dev,>=14.0a)
